stochasticx/__init__.py
stochasticx/auth/__init__.py
stochasticx/auth/auth.py
stochasticx/benchmark/__init__.py
stochasticx/benchmark/local_benchmark.py
stochasticx/client/__init__.py
stochasticx/client/auth.py
stochasticx/client/benchmark.py
stochasticx/client/conversion.py
stochasticx/client/datasets.py
stochasticx/client/deployments.py
stochasticx/client/finetuning.py
stochasticx/client/inferences.py
stochasticx/client/jobs.py
stochasticx/client/local.py
stochasticx/client/models.py
stochasticx/client/preferences.py
stochasticx/client/stable_diffusion.py
stochasticx/constants/__init__.py
stochasticx/constants/docker_images.py
stochasticx/constants/urls.py
stochasticx/conversion/__init__.py
stochasticx/conversion/local_conversion.py
stochasticx/datasets/__init__.py
stochasticx/datasets/datasets.py
stochasticx/deployment/__init__.py
stochasticx/deployment/deployments.py
stochasticx/finetuning/__init__.py
stochasticx/finetuning/finetuning.py
stochasticx/inferences/__init__.py
stochasticx/inferences/inference.py
stochasticx/instances/__init__.py
stochasticx/instances/instance_types.py
stochasticx/jobs/__init__.py
stochasticx/jobs/jobs.py
stochasticx/models/__init__.py
stochasticx/models/models.py
stochasticx/scripts/__init__.py
stochasticx/scripts/stochasticx.py
stochasticx/stable_diffusion/__init__.py
stochasticx/stable_diffusion/download_models.py
stochasticx/stable_diffusion/inference.py
stochasticx/stable_diffusion/stable_diffusion.py
stochasticx/utils/__init__.py
stochasticx/utils/auth_utils.py
stochasticx/utils/docker.py
stochasticx/utils/file_utils.py
stochasticx/utils/gpu_utils.py
stochasticx/utils/inference_utils.py
stochasticx/utils/logging.py
stochasticx/utils/parse_utils.py
stochasticx/utils/preferences.py
stochasticx/utils/spinner_slash.py
stochasticx/utils/stat_controller.py
stochasticx-0.0.19.dist-info/METADATA
stochasticx-0.0.19.dist-info/WHEEL
stochasticx-0.0.19.dist-info/entry_points.txt
stochasticx-0.0.19.dist-info/top_level.txt
stochasticx-0.0.19.dist-info/RECORD
