Metadata-Version: 2.1
Name: stochasticx
Version: 0.0.19
Summary: Stochastic client library
Home-page: https://github.com/stochasticai/stochasticx
Author: Marcos Rivera Martínez, Sarthak Langde, Glenn Ko, Subhash G N, Jolina Li
Author-email: marcos.rm@stochastic.ai, sarthak.langde@stochastic.ai, glenn@stochastic.ai, subhash.gn@stochastic.ai, jolina.li@mail.utoronto.ca
Classifier: Programming Language :: Python :: 3
Classifier: Operating System :: OS Independent
Requires-Python: >=3.6
Requires-Dist: requests (==2.28.1)
Requires-Dist: jwt (==1.3.1)
Requires-Dist: Click (==8.1.3)
Requires-Dist: tqdm (==4.64.1)
Requires-Dist: ipywidgets (==8.0.2)
Requires-Dist: tritonclient[all] (==2.27.0)
Requires-Dist: docker (==6.0.1)
Requires-Dist: numpy (==1.23.4)
Requires-Dist: Pillow (==9.3.0)
Requires-Dist: diffusers (==0.11.1)
Requires-Dist: transformers (==4.25.1)
Requires-Dist: rich (==12.6.0)
Requires-Dist: accelerate (==0.14.0)
Requires-Dist: pydantic (==1.10.2)
Requires-Dist: pandas (==1.5.1)
Provides-Extra: dev
Requires-Dist: pre-commit (==2.20.0) ; extra == 'dev'
